automl_utils/__init__.py
automl_utils/py.typed
automl_utils/nas/__init__.py
automl_utils/nas/phase.py
automl_utils/nas/dataloader/__init__.py
automl_utils/nas/dataloader/darts.py
automl_utils/nas/dataloader/spec.py
automl_utils/nas/dataloader/vision_transforms.py
automl_utils/nas/op_space/__init__.py
automl_utils/nas/op_space/darts.py
automl_utils/nas/op_space/op_space.py
automl_utils/nas/op_space/temp.py
automl_utils/nas/op_space/vision_ops.py
automl_utils/utils/__init__.py
automl_utils/utils/data.py
automl_utils/utils/tensorboard.py
automl_utils-0.1.0a1.dist-info/LICENSE.txt
automl_utils-0.1.0a1.dist-info/METADATA
automl_utils-0.1.0a1.dist-info/WHEEL
automl_utils-0.1.0a1.dist-info/top_level.txt
automl_utils-0.1.0a1.dist-info/RECORD
